offcall/__init__.py
offcall/api_client.py
offcall/cli.py
offcall/config.py
offcall/commands/__init__.py
offcall_cli-1.0.1.dist-info/licenses/LICENSE
offcall_cli-1.0.1.dist-info/METADATA
offcall_cli-1.0.1.dist-info/WHEEL
offcall_cli-1.0.1.dist-info/entry_points.txt
offcall_cli-1.0.1.dist-info/top_level.txt
offcall_cli-1.0.1.dist-info/RECORD
