Metadata-Version: 2.4
Name: offcall-cli
Version: 1.0.1
Summary: OffCall AI Command Line Interface - Manage incidents, alerts, and deployments from your terminal
Home-page: https://github.com/offcall-ai/offcall-cli
Author: OffCall AI
Author-email: OffCall AI <support@offcallai.com>
Maintainer-email: OffCall AI <support@offcallai.com>
License-Expression: MIT
Project-URL: Homepage, https://offcallai.com
Project-URL: Documentation, https://docs.offcallai.com/cli
Project-URL: Repository, https://github.com/offcall-ai/offcall-cli
Project-URL: Issues, https://github.com/offcall-ai/offcall-cli/issues
Project-URL: Changelog, https://github.com/offcall-ai/offcall-cli/blob/main/CHANGELOG.md
Keywords: offcall,incident-management,monitoring,observability,alerting,on-call,devops,sre,cli
Classifier: Development Status :: 4 - Beta
Classifier: Environment :: Console
Classifier: Intended Audience :: Developers
Classifier: Intended Audience :: System Administrators
Classifier: Operating System :: OS Independent
Classifier: Programming Language :: Python :: 3
Classifier: Programming Language :: Python :: 3.8
Classifier: Programming Language :: Python :: 3.9
Classifier: Programming Language :: Python :: 3.10
Classifier: Programming Language :: Python :: 3.11
Classifier: Programming Language :: Python :: 3.12
Classifier: Topic :: System :: Monitoring
Classifier: Topic :: System :: Systems Administration
Classifier: Topic :: Software Development :: Libraries :: Python Modules
Requires-Python: >=3.8
License-File: LICENSE
Requires-Dist: click>=8.0
Requires-Dist: rich>=12.0
Requires-Dist: httpx>=0.23
Requires-Dist: pyyaml>=6.0
Requires-Dist: python-dateutil>=2.8
Provides-Extra: dev
Requires-Dist: pytest>=7.0; extra == "dev"
Requires-Dist: pytest-cov>=4.0; extra == "dev"
Requires-Dist: black>=23.0; extra == "dev"
Requires-Dist: ruff>=0.1.0; extra == "dev"
Requires-Dist: mypy>=1.0; extra == "dev"
Dynamic: author
Dynamic: home-page
Dynamic: license-file
Dynamic: requires-python
